<annotation>
	<folder>compressed</folder>
	<filename>dreamstime_xxl_8093940 - polystyrene food boxts.jpg</filename>
	<path>C:\Users\MSI-GAMMING\Documents\COOLYEAH\Bangkit\Capstone Project\DatasetSampahXML\Dataset\Tensorflow\sterofoam\compressed\dreamstime_xxl_8093940 - polystyrene food boxts.jpg</path>
	<source>
		<database>Unknown</database>
	</source>
	<size>
		<width>640</width>
		<height>360</height>
		<depth>3</depth>
	</size>
	<segmented>0</segmented>
	<object>
		<name>sterofoam</name>
		<pose>Unspecified</pose>
		<truncated>0</truncated>
		<difficult>0</difficult>
		<bndbox>
			<xmin>204</xmin>
			<ymin>64</ymin>
			<xmax>563</xmax>
			<ymax>310</ymax>
		</bndbox>
	</object>
</annotation>
